recommender/__init__.py
recommender/generator.py
recommender/mutual_information.py
recommender/recommender_pipeline.py
chemrecommender-0.0.1.dist-info/METADATA
chemrecommender-0.0.1.dist-info/WHEEL
chemrecommender-0.0.1.dist-info/top_level.txt
chemrecommender-0.0.1.dist-info/RECORD
