Metadata-Version: 2.1
Name: chemrecommender
Version: 0.0.1
Summary: A standalone module to build a recommender pipeline
Home-page: https://github.com/darkreactions/recommendation_engine
Author: DRP Project
Author-email: darkreactionproject@haverford.edu
License: UNKNOWN
Platform: UNKNOWN
Classifier: Programming Language :: Python :: 3
Classifier: License :: OSI Approved :: MIT License
Classifier: Operating System :: OS Independent
Requires-Dist: pandas
Requires-Dist: chemdescriptor
